jdbm.py
setup.py
jdbm.egg-info/PKG-INFO
jdbm.egg-info/SOURCES.txt
jdbm.egg-info/dependency_links.txt
jdbm.egg-info/top_level.txt