Metadata-Version: 1.0
Name: jdbm
Version: 1.0
Summary: Journaling dbm
Home-page: https://github.com/imbolc/jdbm
Author: Imbolc
Author-email: imbolc@imbolc.name
License: ISC
Platform: UNKNOWN
Classifier: Development Status :: 4 - Beta
Classifier: Intended Audience :: Developers
Classifier: License :: OSI Approved :: ISC License (ISCL)
Classifier: Programming Language :: Python
